pymicro_wakeword/__init__.py
pymicro_wakeword/__main__.py
pymicro_wakeword/const.py
pymicro_wakeword/microwakeword.py
pymicro_wakeword/py.typed
pymicro_wakeword/wakeword.py
pymicro_wakeword/lib/tensorflowlite_c.dll
pymicro_wakeword/models/alexa.json
pymicro_wakeword/models/alexa.tflite
pymicro_wakeword/models/hey_jarvis.json
pymicro_wakeword/models/hey_jarvis.tflite
pymicro_wakeword/models/hey_mycroft.json
pymicro_wakeword/models/hey_mycroft.tflite
pymicro_wakeword/models/okay_nabu.json
pymicro_wakeword/models/okay_nabu.tflite
pymicro_wakeword-2.2.1.dist-info/licenses/LICENSE
pymicro_wakeword-2.2.1.dist-info/METADATA
pymicro_wakeword-2.2.1.dist-info/WHEEL
pymicro_wakeword-2.2.1.dist-info/top_level.txt
pymicro_wakeword-2.2.1.dist-info/RECORD
