Metadata-Version: 2.4
Name: pymicro-wakeword
Version: 2.2.1
Summary: A TensorFlow based wake word detection training framework using synthetic sample generation suitable for certain microcontrollers.
Author-email: Michael Hansen <mike@rhasspy.org>
License: Apache-2.0
Project-URL: Source Code, https://github.com/OHF-Voice/pymicro-wakeword
Keywords: wakeword,detection,hotword
Platform: any
Classifier: Development Status :: 3 - Alpha
Classifier: Intended Audience :: Developers
Classifier: Topic :: Multimedia :: Sound/Audio :: Speech
Classifier: License :: OSI Approved :: Apache Software License
Classifier: Programming Language :: Python :: 3.8
Classifier: Programming Language :: Python :: 3.9
Classifier: Programming Language :: Python :: 3.10
Classifier: Programming Language :: Python :: 3.11
Classifier: Programming Language :: Python :: 3.12
Classifier: Programming Language :: Python :: 3.13
Requires-Python: >=3.9.0
License-File: LICENSE
Requires-Dist: pymicro-features<3,>=2
Requires-Dist: numpy
Provides-Extra: dev
Requires-Dist: black; extra == "dev"
Requires-Dist: flake8; extra == "dev"
Requires-Dist: isort; extra == "dev"
Requires-Dist: mypy; extra == "dev"
Requires-Dist: pylint; extra == "dev"
Requires-Dist: pytest; extra == "dev"
Requires-Dist: build; extra == "dev"
Dynamic: license-file
